phylodeep_data_BDEI_large/__init__.py
phylodeep_data_BDEI_large/ci_computation/predicted_values/BDEI_LARGE_CNN.csv.gz
phylodeep_data_BDEI_large/ci_computation/predicted_values/BDEI_LARGE_FFNN.csv.gz
phylodeep_data_BDEI_large/ci_computation/target_values/BDEI_LARGE.csv.gz
phylodeep_data_BDEI_large-0.0.2.dist-info/METADATA
phylodeep_data_BDEI_large-0.0.2.dist-info/WHEEL
phylodeep_data_BDEI_large-0.0.2.dist-info/top_level.txt
phylodeep_data_BDEI_large-0.0.2.dist-info/RECORD
